{
  "protocol": 770,
  "minecraft:mob_effect": {
    "minecraft:absorption": 21,
    "minecraft:bad_omen": 30,
    "minecraft:blindness": 14,
    "minecraft:conduit_power": 28,
    "minecraft:darkness": 32,
    "minecraft:dolphins_grace": 29,
    "minecraft:fire_resistance": 11,
    "minecraft:glowing": 23,
    "minecraft:haste": 2,
    "minecraft:health_boost": 20,
    "minecraft:hero_of_the_village": 31,
    "minecraft:hunger": 16,
    "minecraft:infested": 38,
    "minecraft:instant_damage": 6,
    "minecraft:instant_health": 5,
    "minecraft:invisibility": 13,
    "minecraft:jump_boost": 7,
    "minecraft:levitation": 24,
    "minecraft:luck": 25,
    "minecraft:mining_fatigue": 3,
    "minecraft:nausea": 8,
    "minecraft:night_vision": 15,
    "minecraft:oozing": 37,
    "minecraft:poison": 18,
    "minecraft:raid_omen": 34,
    "minecraft:regeneration": 9,
    "minecraft:resistance": 10,
    "minecraft:saturation": 22,
    "minecraft:slow_falling": 27,
    "minecraft:slowness": 1,
    "minecraft:speed": 0,
    "minecraft:strength": 4,
    "minecraft:trial_omen": 33,
    "minecraft:unluck": 26,
    "minecraft:water_breathing": 12,
    "minecraft:weakness": 17,
    "minecraft:weaving": 36,
    "minecraft:wind_charged": 35,
    "minecraft:wither": 19
  },
  "minecraft:block_entity_type": {
    "minecraft:banner": 20,
    "minecraft:barrel": 27,
    "minecraft:beacon": 15,
    "minecraft:bed": 25,
    "minecraft:beehive": 34,
    "minecraft:bell": 31,
    "minecraft:blast_furnace": 29,
    "minecraft:brewing_stand": 12,
    "minecraft:brushable_block": 40,
    "minecraft:calibrated_sculk_sensor": 36,
    "minecraft:campfire": 33,
    "minecraft:chest": 1,
    "minecraft:chiseled_bookshelf": 39,
    "minecraft:command_block": 23,
    "minecraft:comparator": 19,
    "minecraft:conduit": 26,
    "minecraft:crafter": 42,
    "minecraft:creaking_heart": 10,
    "minecraft:daylight_detector": 17,
    "minecraft:decorated_pot": 41,
    "minecraft:dispenser": 5,
    "minecraft:dropper": 6,
    "minecraft:enchanting_table": 13,
    "minecraft:end_gateway": 22,
    "minecraft:end_portal": 14,
    "minecraft:ender_chest": 3,
    "minecraft:furnace": 0,
    "minecraft:hanging_sign": 8,
    "minecraft:hopper": 18,
    "minecraft:jigsaw": 32,
    "minecraft:jukebox": 4,
    "minecraft:lectern": 30,
    "minecraft:mob_spawner": 9,
    "minecraft:piston": 11,
    "minecraft:sculk_catalyst": 37,
    "minecraft:sculk_sensor": 35,
    "minecraft:sculk_shrieker": 38,
    "minecraft:shulker_box": 24,
    "minecraft:sign": 7,
    "minecraft:skull": 16,
    "minecraft:smoker": 28,
    "minecraft:structure_block": 21,
    "minecraft:test_block": 45,
    "minecraft:test_instance_block": 46,
    "minecraft:trapped_chest": 2,
    "minecraft:trial_spawner": 43,
    "minecraft:vault": 44
  },
  "minecraft:data_component_type": {
    "minecraft:attribute_modifiers": 13,
    "minecraft:axolotl/variant": 91,
    "minecraft:banner_patterns": 63,
    "minecraft:base_color": 64,
    "minecraft:bees": 68,
    "minecraft:block_entity_data": 51,
    "minecraft:block_state": 67,
    "minecraft:blocks_attacks": 33,
    "minecraft:break_sound": 71,
    "minecraft:bucket_entity_data": 50,
    "minecraft:bundle_contents": 41,
    "minecraft:can_break": 12,
    "minecraft:can_place_on": 11,
    "minecraft:cat/collar": 93,
    "minecraft:cat/variant": 92,
    "minecraft:charged_projectiles": 40,
    "minecraft:chicken/variant": 86,
    "minecraft:consumable": 21,
    "minecraft:container": 66,
    "minecraft:container_loot": 70,
    "minecraft:cow/variant": 85,
    "minecraft:creative_slot_lock": 17,
    "minecraft:custom_data": 0,
    "minecraft:custom_model_data": 14,
    "minecraft:custom_name": 5,
    "minecraft:damage": 3,
    "minecraft:damage_resistant": 24,
    "minecraft:death_protection": 32,
    "minecraft:debug_stick_state": 48,
    "minecraft:dyed_color": 35,
    "minecraft:enchantable": 27,
    "minecraft:enchantment_glint_override": 18,
    "minecraft:enchantments": 10,
    "minecraft:entity_data": 49,
    "minecraft:equippable": 28,
    "minecraft:firework_explosion": 59,
    "minecraft:fireworks": 60,
    "minecraft:food": 20,
    "minecraft:fox/variant": 76,
    "minecraft:frog/variant": 87,
    "minecraft:glider": 30,
    "minecraft:horse/variant": 88,
    "minecraft:instrument": 52,
    "minecraft:intangible_projectile": 19,
    "minecraft:item_model": 7,
    "minecraft:item_name": 6,
    "minecraft:jukebox_playable": 55,
    "minecraft:llama/variant": 90,
    "minecraft:lock": 69,
    "minecraft:lodestone_tracker": 58,
    "minecraft:lore": 8,
    "minecraft:map_color": 36,
    "minecraft:map_decorations": 38,
    "minecraft:map_id": 37,
    "minecraft:map_post_processing": 39,
    "minecraft:max_damage": 2,
    "minecraft:max_stack_size": 1,
    "minecraft:mooshroom/variant": 82,
    "minecraft:note_block_sound": 62,
    "minecraft:ominous_bottle_amplifier": 54,
    "minecraft:painting/variant": 89,
    "minecraft:parrot/variant": 78,
    "minecraft:pig/variant": 84,
    "minecraft:pot_decorations": 65,
    "minecraft:potion_contents": 42,
    "minecraft:potion_duration_scale": 43,
    "minecraft:profile": 61,
    "minecraft:provides_banner_patterns": 56,
    "minecraft:provides_trim_material": 53,
    "minecraft:rabbit/variant": 83,
    "minecraft:rarity": 9,
    "minecraft:recipes": 57,
    "minecraft:repair_cost": 16,
    "minecraft:repairable": 29,
    "minecraft:salmon/size": 77,
    "minecraft:sheep/color": 94,
    "minecraft:shulker/color": 95,
    "minecraft:stored_enchantments": 34,
    "minecraft:suspicious_stew_effects": 44,
    "minecraft:tool": 25,
    "minecraft:tooltip_display": 15,
    "minecraft:tooltip_style": 31,
    "minecraft:trim": 47,
    "minecraft:tropical_fish/base_color": 80,
    "minecraft:tropical_fish/pattern": 79,
    "minecraft:tropical_fish/pattern_color": 81,
    "minecraft:unbreakable": 4,
    "minecraft:use_cooldown": 23,
    "minecraft:use_remainder": 22,
    "minecraft:villager/variant": 72,
    "minecraft:weapon": 26,
    "minecraft:wolf/collar": 75,
    "minecraft:wolf/sound_variant": 74,
    "minecraft:wolf/variant": 73,
    "minecraft:writable_book_content": 45,
    "minecraft:written_book_content": 46
  }
}